alumathblackout/__init__.py
alumathblackout/matrix.py
alumathblackout-0.1.1.dist-info/licenses/LICENSE
alumathblackout-0.1.1.dist-info/METADATA
alumathblackout-0.1.1.dist-info/WHEEL
alumathblackout-0.1.1.dist-info/top_level.txt
alumathblackout-0.1.1.dist-info/RECORD
