Metadata-Version: 2.4
Name: alumathblackout
Version: 0.1.1
Summary: A simple matrix multiplication library mimicking NumPy
Author: Egide Harerimana, Sage Muhodari, Raissa Irutingabo, Michael Musa Musembi
License: MIT
Project-URL: homepage, https://github.com/degide/alumathblackout
Project-URL: source, https://github.com/degide/alumathblackout
Keywords: matrix,multiplication,algebra
Classifier: Programming Language :: Python :: 3
Classifier: Operating System :: OS Independent
Requires-Python: >=3.6
License-File: LICENSE
Dynamic: license-file
